Models/APIEnumConverter.py
Models/BarcodeData.py
Models/Classification.py
Models/Data.py
Models/Detail.py
Models/Device.py
Models/DeviceClass.py
Models/Error.py
Models/Fault.py
Models/IResponse.py
Models/Meta.py
Models/MetaResults.py
Models/Offer.py
Models/OpenFDADevice.py
Models/OpenFDAProduct.py
Models/Product.py
Models/ProductType.py
Models/Recall.py
Models/Status.py
Models/__init__.py
Savanna_Python_SDK-1.0.0.dist-info/LICENSE
Savanna_Python_SDK-1.0.0.dist-info/METADATA
Savanna_Python_SDK-1.0.0.dist-info/WHEEL
Savanna_Python_SDK-1.0.0.dist-info/top_level.txt
Savanna_Python_SDK-1.0.0.dist-info/RECORD
