Metadata-Version: 2.1
Name: Savanna-Python-SDK
Version: 1.0.0
Summary: This is the source code for the Savanna Python Software Development Kit (SDK).
Home-page: https://github.com/Zebra/Savanna-Python-SDK
Author: Declan Buhrsmith
Author-email: dbuhrsmith@zebra.com
License: UNKNOWN
Platform: UNKNOWN
Classifier: Programming Language :: Python :: 3
Classifier: License :: OSI Approved :: MIT License
Classifier: Operating System :: OS Independent
Requires-Python: >=3.6
